<?xml version="1.0" encoding="ISO-8859-1" standalone="yes"?>
<TileDesigns>
	<DataChecksum NoParse="1">
		<Ignore>DisplayName</Ignore>
		<Translate>DisplayName</Translate>
	</DataChecksum>
	<TileDesign InternalName="F_Pub_01">
		<DisplayName>F_Pub_01</DisplayName>
		<Thumbnail>\Game\Gfx\tile_icon.png</Thumbnail>
		<DecalName>Gfx\Decals\DirtSquareSmall.png</DecalName>
		<LowResShadow>F_Pub_01_shadow_256.png</LowResShadow>
		<HighResShadow>F_Pub_01_shadow_512.png</HighResShadow>
		<ShadowTransparency>70</ShadowTransparency>
		<IsCore>0</IsCore>
		<IsHiddenFromEditor>0</IsHiddenFromEditor>
		<SubTileFlags>1</SubTileFlags>
		<TileDesignObject InternalName="_obj0">
			<ObjectType>PropModelType</ObjectType>
			<ObjectDefName>F_BuildBlock_Wood_Large_01</ObjectDefName>
			<ObjectLOD>1</ObjectLOD>
			<IgnoreTerrain>1</IgnoreTerrain>
			<Position>4.000000,0.000000,8.250000</Position>
			<Rotation>0.000000,-6.283187,0.000000</Rotation>
			<RotationSpeed>0.000000,0.000000,0.000000</RotationSpeed>
			<Scale>0.9600</Scale>
			<BaseScale>1.0000</BaseScale>
		</TileDesignObject>
		<TileDesignObject InternalName="_obj1">
			<ObjectType>PropModelType</ObjectType>
			<ObjectDefName>F_Roof_Tile_Large_01</ObjectDefName>
			<ObjectLOD>1</ObjectLOD>
			<IgnoreTerrain>1</IgnoreTerrain>
			<Position>4.000000,21.000000,8.250000</Position>
			<Rotation>0.000000,0.000000,0.000000</Rotation>
			<RotationSpeed>0.000000,0.000000,0.000000</RotationSpeed>
			<Scale>0.8000</Scale>
			<BaseScale>1.0000</BaseScale>
		</TileDesignObject>
		<TileDesignObject InternalName="_obj2">
			<ObjectType>PropModelType</ObjectType>
			<ObjectDefName>F_Door1</ObjectDefName>
			<ObjectLOD>5</ObjectLOD>
			<IgnoreTerrain>1</IgnoreTerrain>
			<Position>4.125000,0.000000,-1.687500</Position>
			<Rotation>0.261799,0.000000,0.000000</Rotation>
			<RotationSpeed>0.000000,0.000000,0.000000</RotationSpeed>
			<Scale>1.0000</Scale>
			<BaseScale>1.4000</BaseScale>
		</TileDesignObject>
		<TileDesignObject InternalName="_obj3">
			<ObjectType>PropModelType</ObjectType>
			<ObjectDefName>F_Door1</ObjectDefName>
			<ObjectLOD>6</ObjectLOD>
			<IgnoreTerrain>1</IgnoreTerrain>
			<Position>-10.625000,0.000000,8.250000</Position>
			<Rotation>0.174533,1.570796,0.000000</Rotation>
			<RotationSpeed>0.000000,0.000000,0.000000</RotationSpeed>
			<Scale>1.0800</Scale>
			<BaseScale>1.4000</BaseScale>
		</TileDesignObject>
		<TileDesignObject InternalName="_obj4">
			<ObjectType>PropModelType</ObjectType>
			<ObjectDefName>F_ScaffoldSmall</ObjectDefName>
			<ObjectLOD>4</ObjectLOD>
			<IgnoreTerrain>1</IgnoreTerrain>
			<Position>15.062500,-8.000000,-14.187500</Position>
			<Rotation>0.000000,-0.499066,0.000000</Rotation>
			<RotationSpeed>0.000000,0.000000,0.000000</RotationSpeed>
			<Scale>1.0400</Scale>
			<BaseScale>1.4000</BaseScale>
		</TileDesignObject>
		<TileDesignObject InternalName="_obj5">
			<ObjectType>PropModelType</ObjectType>
			<ObjectDefName>F_ScaffoldSmall</ObjectDefName>
			<ObjectLOD>4</ObjectLOD>
			<IgnoreTerrain>1</IgnoreTerrain>
			<Position>-1.687500,-7.000000,-15.187500</Position>
			<Rotation>0.000000,0.150000,0.000000</Rotation>
			<RotationSpeed>0.000000,0.000000,0.000000</RotationSpeed>
			<Scale>0.9600</Scale>
			<BaseScale>1.4000</BaseScale>
		</TileDesignObject>
		<TileDesignObject InternalName="_obj6">
			<ObjectType>PropModelType</ObjectType>
			<ObjectDefName>F_ShrineCanopy</ObjectDefName>
			<ObjectLOD>3</ObjectLOD>
			<IgnoreTerrain>1</IgnoreTerrain>
			<Position>-12.107483,1.000000,8.143773</Position>
			<Rotation>0.000000,0.000000,0.087266</Rotation>
			<RotationSpeed>0.000000,0.000000,0.000000</RotationSpeed>
			<Scale>0.8000</Scale>
			<BaseScale>1.4000</BaseScale>
		</TileDesignObject>
		<TileDesignObject InternalName="_obj7">
			<ObjectType>PropModelType</ObjectType>
			<ObjectDefName>F_Chimney</ObjectDefName>
			<ObjectLOD>3</ObjectLOD>
			<IgnoreTerrain>1</IgnoreTerrain>
			<Position>3.125000,0.000000,18.750000</Position>
			<Rotation>0.000000,-1.570796,0.000000</Rotation>
			<RotationSpeed>0.000000,0.000000,0.000000</RotationSpeed>
			<Scale>1.0800</Scale>
			<BaseScale>1.4000</BaseScale>
		</TileDesignObject>
		<TileDesignObject InternalName="_obj8">
			<ObjectType>PropModelType</ObjectType>
			<ObjectDefName>F_Rockpit</ObjectDefName>
			<ObjectLOD>5</ObjectLOD>
			<IgnoreTerrain>1</IgnoreTerrain>
			<Position>-17.187500,0.000000,-14.062500</Position>
			<Rotation>0.000000,0.000000,0.000000</Rotation>
			<RotationSpeed>0.000000,0.000000,0.000000</RotationSpeed>
			<Scale>0.9200</Scale>
			<BaseScale>1.4000</BaseScale>
		</TileDesignObject>
		<TileDesignObject InternalName="_obj9">
			<ObjectType>PropModelType</ObjectType>
			<ObjectDefName>F_Pot</ObjectDefName>
			<ObjectLOD>4</ObjectLOD>
			<IgnoreTerrain>1</IgnoreTerrain>
			<Position>-17.187500,1.000000,-14.062500</Position>
			<Rotation>0.000000,-0.436332,0.000000</Rotation>
			<RotationSpeed>0.000000,0.000000,0.000000</RotationSpeed>
			<Scale>1.0000</Scale>
			<BaseScale>1.4000</BaseScale>
		</TileDesignObject>
		<TileDesignObject InternalName="_obj10">
			<ObjectType>PropModelType</ObjectType>
			<ObjectDefName>F_Bench</ObjectDefName>
			<ObjectLOD>6</ObjectLOD>
			<IgnoreTerrain>1</IgnoreTerrain>
			<Position>-17.657669,0.000000,13.131584</Position>
			<Rotation>0.000000,0.000000,0.000000</Rotation>
			<RotationSpeed>0.000000,0.000000,0.000000</RotationSpeed>
			<Scale>0.9200</Scale>
			<BaseScale>1.4000</BaseScale>
		</TileDesignObject>
		<TileDesignObject InternalName="_obj11">
			<ObjectType>PropModelType</ObjectType>
			<ObjectDefName>F_Bench</ObjectDefName>
			<ObjectLOD>6</ObjectLOD>
			<IgnoreTerrain>1</IgnoreTerrain>
			<Position>-1.317524,0.000000,-9.631340</Position>
			<Rotation>0.000000,0.150000,0.000000</Rotation>
			<RotationSpeed>0.000000,0.000000,0.000000</RotationSpeed>
			<Scale>1.0000</Scale>
			<BaseScale>1.4000</BaseScale>
		</TileDesignObject>
		<TileDesignObject InternalName="_obj12">
			<ObjectType>PropModelType</ObjectType>
			<ObjectDefName>F_Bench</ObjectDefName>
			<ObjectLOD>6</ObjectLOD>
			<IgnoreTerrain>1</IgnoreTerrain>
			<Position>-2.300697,0.000000,-21.105885</Position>
			<Rotation>0.000000,0.225000,0.000000</Rotation>
			<RotationSpeed>0.000000,0.000000,0.000000</RotationSpeed>
			<Scale>1.0000</Scale>
			<BaseScale>1.4000</BaseScale>
		</TileDesignObject>
		<TileDesignObject InternalName="_obj13">
			<ObjectType>PropModelType</ObjectType>
			<ObjectDefName>F_Bench</ObjectDefName>
			<ObjectLOD>6</ObjectLOD>
			<IgnoreTerrain>1</IgnoreTerrain>
			<Position>12.352798,0.000000,-9.326427</Position>
			<Rotation>0.000000,-0.450000,0.000000</Rotation>
			<RotationSpeed>0.000000,0.000000,0.000000</RotationSpeed>
			<Scale>1.0000</Scale>
			<BaseScale>1.4000</BaseScale>
		</TileDesignObject>
		<TileDesignObject InternalName="_obj14">
			<ObjectType>PropModelType</ObjectType>
			<ObjectDefName>F_Bench</ObjectDefName>
			<ObjectLOD>6</ObjectLOD>
			<IgnoreTerrain>1</IgnoreTerrain>
			<Position>17.968369,0.000000,-19.012676</Position>
			<Rotation>0.000000,-0.512734,0.000000</Rotation>
			<RotationSpeed>0.000000,0.000000,0.000000</RotationSpeed>
			<Scale>1.0000</Scale>
			<BaseScale>1.4000</BaseScale>
		</TileDesignObject>
		<TileDesignObject InternalName="_obj15">
			<ObjectType>PropModelType</ObjectType>
			<ObjectDefName>F_Keep_Flag2</ObjectDefName>
			<ObjectLOD>6</ObjectLOD>
			<IgnoreTerrain>0</IgnoreTerrain>
			<Position>12.629988,17.000000,-2.316422</Position>
			<Rotation>0.000000,0.000000,0.000000</Rotation>
			<RotationSpeed>0.000000,0.000000,0.000000</RotationSpeed>
			<Scale>0.4400</Scale>
			<BaseScale>5.0000</BaseScale>
		</TileDesignObject>
		<TileDesignObject InternalName="_obj16">
			<ObjectType>PropModelType</ObjectType>
			<ObjectDefName>F_Keep_Flag2</ObjectDefName>
			<ObjectLOD>6</ObjectLOD>
			<IgnoreTerrain>0</IgnoreTerrain>
			<Position>-4.976201,17.000000,-2.766891</Position>
			<Rotation>0.000000,0.000000,0.000000</Rotation>
			<RotationSpeed>0.000000,0.000000,0.000000</RotationSpeed>
			<Scale>0.4800</Scale>
			<BaseScale>5.0000</BaseScale>
		</TileDesignObject>
		<TileDesignObject InternalName="_obj17">
			<ObjectType>PropModelType</ObjectType>
			<ObjectDefName>F_Barrel</ObjectDefName>
			<ObjectLOD>5</ObjectLOD>
			<IgnoreTerrain>1</IgnoreTerrain>
			<Position>-17.808254,0.000000,19.751205</Position>
			<Rotation>0.000000,-0.225000,0.000000</Rotation>
			<RotationSpeed>0.000000,0.000000,0.000000</RotationSpeed>
			<Scale>1.0000</Scale>
			<BaseScale>1.4000</BaseScale>
		</TileDesignObject>
		<TileDesignObject InternalName="_obj18">
			<ObjectType>PropModelType</ObjectType>
			<ObjectDefName>F_WaterTroughSmall</ObjectDefName>
			<ObjectLOD>6</ObjectLOD>
			<IgnoreTerrain>1</IgnoreTerrain>
			<Position>-19.794498,0.000000,-4.266171</Position>
			<Rotation>0.000000,-0.150000,0.000000</Rotation>
			<RotationSpeed>0.000000,0.000000,0.000000</RotationSpeed>
			<Scale>1.2800</Scale>
			<BaseScale>1.4000</BaseScale>
		</TileDesignObject>
		<TileDesignObject InternalName="_obj19">
			<ObjectType>PropModelType</ObjectType>
			<ObjectDefName>FallenFemaleMaleAtMarket</ObjectDefName>
			<ObjectLOD>4</ObjectLOD>
			<IgnoreTerrain>0</IgnoreTerrain>
			<Position>-11.964149,0.000000,-11.663071</Position>
			<Rotation>0.000000,1.125000,0.000000</Rotation>
			<RotationSpeed>0.000000,0.000000,0.000000</RotationSpeed>
			<Scale>1.0000</Scale>
			<BaseScale>0.1300</BaseScale>
		</TileDesignObject>
		<TileDesignObject InternalName="_obj20">
			<ObjectType>PropModelType</ObjectType>
			<ObjectDefName>FallenFemaleSitting2</ObjectDefName>
			<ObjectLOD>4</ObjectLOD>
			<IgnoreTerrain>0</IgnoreTerrain>
			<Position>-4.125771,0.000000,-19.166473</Position>
			<Rotation>0.000000,-2.700000,0.000000</Rotation>
			<RotationSpeed>0.000000,0.000000,0.000000</RotationSpeed>
			<Scale>1.0000</Scale>
			<BaseScale>0.1300</BaseScale>
		</TileDesignObject>
		<TileDesignObject InternalName="_obj21">
			<ObjectType>PropModelType</ObjectType>
			<ObjectDefName>FallenWarriorFemaleSitting2</ObjectDefName>
			<ObjectLOD>4</ObjectLOD>
			<IgnoreTerrain>0</IgnoreTerrain>
			<Position>0.353897,0.000000,-20.039238</Position>
			<Rotation>0.000000,3.075001,0.000000</Rotation>
			<RotationSpeed>0.000000,0.000000,0.000000</RotationSpeed>
			<Scale>1.0000</Scale>
			<BaseScale>0.1300</BaseScale>
		</TileDesignObject>
		<TileDesignObject InternalName="_obj22">
			<ObjectType>PropModelType</ObjectType>
			<ObjectDefName>FallenWarriorFemaleSitting1</ObjectDefName>
			<ObjectLOD>4</ObjectLOD>
			<IgnoreTerrain>0</IgnoreTerrain>
			<Position>12.973976,0.000000,-10.250208</Position>
			<Rotation>0.000000,-0.600000,0.000000</Rotation>
			<RotationSpeed>0.000000,0.000000,0.000000</RotationSpeed>
			<Scale>1.0000</Scale>
			<BaseScale>0.1300</BaseScale>
		</TileDesignObject>
		<TileDesignObject InternalName="_obj23">
			<ObjectType>PropModelType</ObjectType>
			<ObjectDefName>FallenMaleSitting2</ObjectDefName>
			<ObjectLOD>4</ObjectLOD>
			<IgnoreTerrain>0</IgnoreTerrain>
			<Position>17.957420,0.000000,-17.316683</Position>
			<Rotation>0.000000,2.400001,0.000000</Rotation>
			<RotationSpeed>0.000000,0.000000,0.000000</RotationSpeed>
			<Scale>1.0000</Scale>
			<BaseScale>0.1350</BaseScale>
		</TileDesignObject>
		<TileDesignObject InternalName="_obj24">
			<ObjectType>PropModelType</ObjectType>
			<ObjectDefName>FallenMaleSitting2</ObjectDefName>
			<ObjectLOD>4</ObjectLOD>
			<IgnoreTerrain>0</IgnoreTerrain>
			<Position>-1.307419,0.000000,-10.957481</Position>
			<Rotation>0.000000,0.150000,0.000000</Rotation>
			<RotationSpeed>0.000000,0.000000,0.000000</RotationSpeed>
			<Scale>1.0000</Scale>
			<BaseScale>0.1350</BaseScale>
		</TileDesignObject>
		<TileDesignObject InternalName="_obj25">
			<ObjectType>PropModelType</ObjectType>
			<ObjectDefName>FallenMaleTalking1</ObjectDefName>
			<ObjectLOD>4</ObjectLOD>
			<IgnoreTerrain>0</IgnoreTerrain>
			<Position>-21.483246,0.000000,4.917486</Position>
			<Rotation>0.000000,-2.100000,0.000000</Rotation>
			<RotationSpeed>0.000000,0.000000,0.000000</RotationSpeed>
			<Scale>1.0000</Scale>
			<BaseScale>0.1350</BaseScale>
		</TileDesignObject>
		<TileDesignObject InternalName="_obj26">
			<ObjectType>PropModelType</ObjectType>
			<ObjectDefName>FallenFemaleTalking1</ObjectDefName>
			<ObjectLOD>4</ObjectLOD>
			<IgnoreTerrain>0</IgnoreTerrain>
			<Position>-17.469971,0.000000,8.422195</Position>
			<Rotation>0.000000,0.975000,0.000000</Rotation>
			<RotationSpeed>0.000000,0.000000,0.000000</RotationSpeed>
			<Scale>1.0000</Scale>
			<BaseScale>0.1300</BaseScale>
		</TileDesignObject>
		<TileDesignObject InternalName="_obj27">
			<ObjectType>PropModelType</ObjectType>
			<ObjectDefName>FallenPlant_Pod</ObjectDefName>
			<ObjectLOD>6</ObjectLOD>
			<IgnoreTerrain>1</IgnoreTerrain>
			<Position>17.101837,4.000000,-12.859363</Position>
			<Rotation>0.000000,0.000000,0.000000</Rotation>
			<RotationSpeed>0.000000,0.000000,0.000000</RotationSpeed>
			<Scale>0.4400</Scale>
			<BaseScale>1.0000</BaseScale>
		</TileDesignObject>
		<TileDesignObject InternalName="_obj28">
			<ObjectType>PropModelType</ObjectType>
			<ObjectDefName>Artifact_RibCage</ObjectDefName>
			<ObjectLOD>6</ObjectLOD>
			<IgnoreTerrain>1</IgnoreTerrain>
			<Position>-2.307132,6.000000,-15.239826</Position>
			<Rotation>3.141593,-1.575000,0.000000</Rotation>
			<RotationSpeed>0.000000,0.000000,0.000000</RotationSpeed>
			<Scale>0.1200</Scale>
			<BaseScale>1.0000</BaseScale>
		</TileDesignObject>
		<TileDesignObject InternalName="_obj29">
			<ObjectType>PropModelType</ObjectType>
			<ObjectDefName>Artifact_Bone</ObjectDefName>
			<ObjectLOD>6</ObjectLOD>
			<IgnoreTerrain>1</IgnoreTerrain>
			<Position>0.963435,5.000000,-17.453585</Position>
			<Rotation>0.000000,-0.675000,0.000000</Rotation>
			<RotationSpeed>0.000000,0.000000,0.000000</RotationSpeed>
			<Scale>0.0800</Scale>
			<BaseScale>1.0000</BaseScale>
		</TileDesignObject>
		<TileDesignObject InternalName="_obj30">
			<ObjectType>PropModelType</ObjectType>
			<ObjectDefName>Artifact_Bone</ObjectDefName>
			<ObjectLOD>4</ObjectLOD>
			<IgnoreTerrain>1</IgnoreTerrain>
			<Position>-0.026300,5.000000,-17.637920</Position>
			<Rotation>0.000000,-1.950000,0.000000</Rotation>
			<RotationSpeed>0.000000,0.000000,0.000000</RotationSpeed>
			<Scale>0.0800</Scale>
			<BaseScale>1.0000</BaseScale>
		</TileDesignObject>
		<TileDesignObject InternalName="_obj31">
			<ObjectType>PropModelType</ObjectType>
			<ObjectDefName>Artifact_Bone</ObjectDefName>
			<ObjectLOD>6</ObjectLOD>
			<IgnoreTerrain>1</IgnoreTerrain>
			<Position>-1.930508,5.000000,-12.603581</Position>
			<Rotation>0.000000,-1.275000,0.000000</Rotation>
			<RotationSpeed>0.000000,0.000000,0.000000</RotationSpeed>
			<Scale>0.0800</Scale>
			<BaseScale>1.0000</BaseScale>
		</TileDesignObject>
		<TileDesignObject InternalName="_obj32">
			<ObjectType>PropModelType</ObjectType>
			<ObjectDefName>Artifact_Bone</ObjectDefName>
			<ObjectLOD>6</ObjectLOD>
			<IgnoreTerrain>1</IgnoreTerrain>
			<Position>-0.852926,5.000000,-12.947098</Position>
			<Rotation>0.000000,-2.325001,0.000000</Rotation>
			<RotationSpeed>0.000000,0.000000,0.000000</RotationSpeed>
			<Scale>0.0800</Scale>
			<BaseScale>1.0000</BaseScale>
		</TileDesignObject>
		<TileDesignObject InternalName="_obj33">
			<ObjectType>PropModelType</ObjectType>
			<ObjectDefName>Artifact_Bone</ObjectDefName>
			<ObjectLOD>6</ObjectLOD>
			<IgnoreTerrain>1</IgnoreTerrain>
			<Position>-4.882515,5.000000,-17.252230</Position>
			<Rotation>0.000000,-1.050000,0.000000</Rotation>
			<RotationSpeed>0.000000,0.000000,0.000000</RotationSpeed>
			<Scale>0.0800</Scale>
			<BaseScale>1.0000</BaseScale>
		</TileDesignObject>
		<TileDesignObject InternalName="_obj34">
			<ObjectType>PropModelType</ObjectType>
			<ObjectDefName>Artifact_Bone</ObjectDefName>
			<ObjectLOD>6</ObjectLOD>
			<IgnoreTerrain>1</IgnoreTerrain>
			<Position>-4.140008,5.000000,-17.185219</Position>
			<Rotation>0.000000,-0.900000,0.000000</Rotation>
			<RotationSpeed>0.000000,0.000000,0.000000</RotationSpeed>
			<Scale>0.0800</Scale>
			<BaseScale>1.0000</BaseScale>
		</TileDesignObject>
		<TileDesignObject InternalName="_obj35">
			<ObjectType>PropModelType</ObjectType>
			<ObjectDefName>Artifact_Bone</ObjectDefName>
			<ObjectLOD>6</ObjectLOD>
			<IgnoreTerrain>1</IgnoreTerrain>
			<Position>17.721279,5.000000,-15.646252</Position>
			<Rotation>0.000000,-1.725000,0.000000</Rotation>
			<RotationSpeed>0.000000,0.000000,0.000000</RotationSpeed>
			<Scale>0.0800</Scale>
			<BaseScale>1.0000</BaseScale>
		</TileDesignObject>
		<TileDesignObject InternalName="_obj36">
			<ObjectType>PropModelType</ObjectType>
			<ObjectDefName>Artifact_Bone</ObjectDefName>
			<ObjectLOD>6</ObjectLOD>
			<IgnoreTerrain>1</IgnoreTerrain>
			<Position>16.728588,5.000000,-16.311560</Position>
			<Rotation>0.000000,-1.275000,0.000000</Rotation>
			<RotationSpeed>0.000000,0.000000,0.000000</RotationSpeed>
			<Scale>0.0800</Scale>
			<BaseScale>1.0000</BaseScale>
		</TileDesignObject>
		<TileDesignObject InternalName="_obj37">
			<ObjectType>PropModelType</ObjectType>
			<ObjectDefName>Artifact_Bone</ObjectDefName>
			<ObjectLOD>6</ObjectLOD>
			<IgnoreTerrain>1</IgnoreTerrain>
			<Position>14.624518,5.000000,-11.486319</Position>
			<Rotation>0.000000,-0.900000,0.000000</Rotation>
			<RotationSpeed>0.000000,0.000000,0.000000</RotationSpeed>
			<Scale>0.0800</Scale>
			<BaseScale>1.0000</BaseScale>
		</TileDesignObject>
		<TileDesignObject InternalName="_obj38">
			<ObjectType>PropModelType</ObjectType>
			<ObjectDefName>F_Keep_WoodenPlankShort</ObjectDefName>
			<ObjectLOD>5</ObjectLOD>
			<IgnoreTerrain>1</IgnoreTerrain>
			<Position>17.179016,5.000000,-15.847185</Position>
			<Rotation>0.000000,0.525000,0.000000</Rotation>
			<RotationSpeed>0.000000,0.000000,0.000000</RotationSpeed>
			<Scale>0.2400</Scale>
			<BaseScale>5.0000</BaseScale>
		</TileDesignObject>
		<TileDesignObject InternalName="_obj39">
			<ObjectType>PropModelType</ObjectType>
			<ObjectDefName>F_Keep_WoodenPlankShort</ObjectDefName>
			<ObjectLOD>5</ObjectLOD>
			<IgnoreTerrain>1</IgnoreTerrain>
			<Position>13.851924,5.000000,-11.906578</Position>
			<Rotation>0.000000,1.200000,0.000000</Rotation>
			<RotationSpeed>0.000000,0.000000,0.000000</RotationSpeed>
			<Scale>0.2400</Scale>
			<BaseScale>5.0000</BaseScale>
		</TileDesignObject>
		<TileDesignObject InternalName="_obj40">
			<ObjectType>PropModelType</ObjectType>
			<ObjectDefName>F_Keep_WoodenPlankShort</ObjectDefName>
			<ObjectLOD>5</ObjectLOD>
			<IgnoreTerrain>1</IgnoreTerrain>
			<Position>-2.263127,5.000000,-15.068134</Position>
			<Rotation>0.000000,1.725000,0.000000</Rotation>
			<RotationSpeed>0.000000,0.000000,0.000000</RotationSpeed>
			<Scale>0.4400</Scale>
			<BaseScale>5.0000</BaseScale>
		</TileDesignObject>
		<TileDesignObject InternalName="_obj41">
			<ObjectType>PropModelType</ObjectType>
			<ObjectDefName>F_Keep_WoodenPlankShort</ObjectDefName>
			<ObjectLOD>5</ObjectLOD>
			<IgnoreTerrain>1</IgnoreTerrain>
			<Position>0.448305,5.000000,-17.593388</Position>
			<Rotation>0.000000,1.500000,0.000000</Rotation>
			<RotationSpeed>0.000000,0.000000,0.000000</RotationSpeed>
			<Scale>0.2800</Scale>
			<BaseScale>5.0000</BaseScale>
		</TileDesignObject>
		<TileDesignObject InternalName="_obj42">
			<ObjectType>PropModelType</ObjectType>
			<ObjectDefName>F_Barrel</ObjectDefName>
			<ObjectLOD>5</ObjectLOD>
			<IgnoreTerrain>1</IgnoreTerrain>
			<Position>-21.545506,0.000000,21.705357</Position>
			<Rotation>0.000000,0.000000,0.000000</Rotation>
			<RotationSpeed>0.000000,0.000000,0.000000</RotationSpeed>
			<Scale>1.0400</Scale>
			<BaseScale>1.4000</BaseScale>
		</TileDesignObject>
		<TileDesignObject InternalName="_obj43">
			<ObjectType>PropModelType</ObjectType>
			<ObjectDefName>F_Barrel</ObjectDefName>
			<ObjectLOD>4</ObjectLOD>
			<IgnoreTerrain>1</IgnoreTerrain>
			<Position>0.571098,4.000000,-13.473091</Position>
			<Rotation>0.174533,0.000000,0.000000</Rotation>
			<RotationSpeed>0.000000,0.000000,0.000000</RotationSpeed>
			<Scale>0.4400</Scale>
			<BaseScale>1.4000</BaseScale>
		</TileDesignObject>
		<TileDesignObject InternalName="_obj44">
			<ObjectType>PropModelType</ObjectType>
			<ObjectDefName>F_Barrel</ObjectDefName>
			<ObjectLOD>5</ObjectLOD>
			<IgnoreTerrain>1</IgnoreTerrain>
			<Position>14.039768,4.000000,-13.970070</Position>
			<Rotation>0.087266,0.000000,0.000000</Rotation>
			<RotationSpeed>0.000000,0.000000,0.000000</RotationSpeed>
			<Scale>0.4400</Scale>
			<BaseScale>1.4000</BaseScale>
		</TileDesignObject>
		<TileDesignPath InternalName="_path0"/>
		<EffectTrigger InternalName="ChimneySmokeNew">
			<EffectName>ChimneySmokeNew</EffectName>
			<LocalPosition>4.762314,27.000000,18.261887</LocalPosition>
			<Scale>0.5000</Scale>
			<IndefiniteRepeat>1</IndefiniteRepeat>
			<SpawnOnCreation>1</SpawnOnCreation>
		</EffectTrigger>
	</TileDesign>
</TileDesigns>
