<?xml version="1.0" encoding="ISO-8859-1" standalone="yes"?>
<TileDesigns>
	<DataChecksum NoParse="1">
		<Ignore>DisplayName</Ignore>
		<Translate>DisplayName</Translate>
	</DataChecksum>
	<TileDesign InternalName="K_Herbalist_01">
		<DisplayName>K_Herbalist_01</DisplayName>
		<Thumbnail>\Game\Gfx\tile_icon.png</Thumbnail>
		<DecalName>Gfx\Decals\DirtSquareSmall.dds</DecalName>
		<LowResShadow>K_Herbalist_01_shadow.png</LowResShadow>
		<HighResShadow>K_Herbalist_01_shadow.png</HighResShadow>
		<ShadowTransparency>70</ShadowTransparency>
		<IsCore>0</IsCore>
		<IsHiddenFromEditor>0</IsHiddenFromEditor>
		<SubTileFlags>1</SubTileFlags>
		<TileDesignObject InternalName="_obj0">
			<ObjectType>PropModelType</ObjectType>
			<ObjectDefName>GrasslandRock_Flat2</ObjectDefName>
			<ObjectLOD>1</ObjectLOD>
			<IgnoreTerrain>1</IgnoreTerrain>
			<Position>-5.622894,0.000000,6.776020</Position>
			<Rotation>0.000000,-2.700001,0.000000</Rotation>
			<RotationSpeed>0.000000,0.000000,0.000000</RotationSpeed>
			<Scale>1.8400</Scale>
			<BaseScale>1.0000</BaseScale>
		</TileDesignObject>
		<TileDesignObject InternalName="_obj1">
			<ObjectType>PropModelType</ObjectType>
			<ObjectDefName>GrasslandRock_Flat1</ObjectDefName>
			<ObjectLOD>1</ObjectLOD>
			<IgnoreTerrain>1</IgnoreTerrain>
			<Position>-2.343740,3.000000,10.514988</Position>
			<Rotation>0.000000,-1.200000,0.000000</Rotation>
			<RotationSpeed>0.000000,0.000000,0.000000</RotationSpeed>
			<Scale>1.2000</Scale>
			<BaseScale>1.0000</BaseScale>
		</TileDesignObject>
		<TileDesignObject InternalName="_obj2">
			<ObjectType>PropModelType</ObjectType>
			<ObjectDefName>GrasslandRock_Flat1</ObjectDefName>
			<ObjectLOD>1</ObjectLOD>
			<IgnoreTerrain>1</IgnoreTerrain>
			<Position>-10.007321,3.000000,3.536213</Position>
			<Rotation>0.000000,-3.450001,0.000000</Rotation>
			<RotationSpeed>0.000000,0.000000,0.000000</RotationSpeed>
			<Scale>1.1600</Scale>
			<BaseScale>1.0000</BaseScale>
		</TileDesignObject>
		<TileDesignObject InternalName="_obj3">
			<ObjectType>PropModelType</ObjectType>
			<ObjectDefName>GrasslandRock_Flat3</ObjectDefName>
			<ObjectLOD>1</ObjectLOD>
			<IgnoreTerrain>1</IgnoreTerrain>
			<Position>-8.469309,5.000000,9.704798</Position>
			<Rotation>0.000000,-3.774534,0.000000</Rotation>
			<RotationSpeed>0.000000,0.000000,0.000000</RotationSpeed>
			<Scale>1.1600</Scale>
			<BaseScale>1.0000</BaseScale>
		</TileDesignObject>
		<TileDesignObject InternalName="_obj4">
			<ObjectType>PropModelType</ObjectType>
			<ObjectDefName>K_Small_House_Basic_01</ObjectDefName>
			<ObjectLOD>1</ObjectLOD>
			<IgnoreTerrain>1</IgnoreTerrain>
			<Position>-7.188324,7.000000,8.522209</Position>
			<Rotation>0.000000,-0.750000,0.000000</Rotation>
			<RotationSpeed>0.000000,0.000000,0.000000</RotationSpeed>
			<Scale>1.0000</Scale>
			<BaseScale>1.0000</BaseScale>
		</TileDesignObject>
		<TileDesignObject InternalName="_obj5">
			<ObjectType>PropModelType</ObjectType>
			<ObjectDefName>K_Stone_Steps_01</ObjectDefName>
			<ObjectLOD>3</ObjectLOD>
			<IgnoreTerrain>1</IgnoreTerrain>
			<Position>-0.018984,3.000000,0.966493</Position>
			<Rotation>0.000000,2.400001,0.000000</Rotation>
			<RotationSpeed>0.000000,0.000000,0.000000</RotationSpeed>
			<Scale>1.0000</Scale>
			<BaseScale>1.0000</BaseScale>
		</TileDesignObject>
		<TileDesignObject InternalName="_obj6">
			<ObjectType>PropModelType</ObjectType>
			<ObjectDefName>K_Stone_Steps_01</ObjectDefName>
			<ObjectLOD>3</ObjectLOD>
			<IgnoreTerrain>1</IgnoreTerrain>
			<Position>2.612253,0.000000,-2.000552</Position>
			<Rotation>0.000000,2.400001,0.000000</Rotation>
			<RotationSpeed>0.000000,0.000000,0.000000</RotationSpeed>
			<Scale>1.0000</Scale>
			<BaseScale>1.0000</BaseScale>
		</TileDesignObject>
		<TileDesignObject InternalName="_obj7">
			<ObjectType>PropModelType</ObjectType>
			<ObjectDefName>GrasslandRock_Small1</ObjectDefName>
			<ObjectLOD>4</ObjectLOD>
			<IgnoreTerrain>1</IgnoreTerrain>
			<Position>-4.406048,-2.000000,18.452072</Position>
			<Rotation>0.000000,-1.650000,0.000000</Rotation>
			<RotationSpeed>0.000000,0.000000,0.000000</RotationSpeed>
			<Scale>1.0000</Scale>
			<BaseScale>1.0000</BaseScale>
		</TileDesignObject>
		<TileDesignObject InternalName="_obj8">
			<ObjectType>PropModelType</ObjectType>
			<ObjectDefName>GrasslandRock_Small2</ObjectDefName>
			<ObjectLOD>4</ObjectLOD>
			<IgnoreTerrain>1</IgnoreTerrain>
			<Position>-16.506321,1.000000,7.574293</Position>
			<Rotation>0.000000,0.000000,0.000000</Rotation>
			<RotationSpeed>0.000000,0.000000,0.000000</RotationSpeed>
			<Scale>1.1600</Scale>
			<BaseScale>1.0000</BaseScale>
		</TileDesignObject>
		<TileDesignObject InternalName="_obj9">
			<ObjectType>PropModelType</ObjectType>
			<ObjectDefName>Artifact_MediumDeadTree3</ObjectDefName>
			<ObjectLOD>5</ObjectLOD>
			<IgnoreTerrain>1</IgnoreTerrain>
			<Position>-15.907269,5.000000,-15.680202</Position>
			<Rotation>0.000000,-3.225001,0.000000</Rotation>
			<RotationSpeed>0.000000,0.000000,0.000000</RotationSpeed>
			<Scale>0.4000</Scale>
			<BaseScale>1.0000</BaseScale>
		</TileDesignObject>
		<TileDesignObject InternalName="_obj10">
			<ObjectType>PropModelType</ObjectType>
			<ObjectDefName>K_Log_Big_01</ObjectDefName>
			<ObjectLOD>4</ObjectLOD>
			<IgnoreTerrain>1</IgnoreTerrain>
			<Position>8.582611,0.000000,-2.193085</Position>
			<Rotation>0.000000,0.675000,0.000000</Rotation>
			<RotationSpeed>0.000000,0.000000,0.000000</RotationSpeed>
			<Scale>0.4800</Scale>
			<BaseScale>1.0000</BaseScale>
		</TileDesignObject>
		<TileDesignObject InternalName="_obj11">
			<ObjectType>PropModelType</ObjectType>
			<ObjectDefName>K_Log_Small_01</ObjectDefName>
			<ObjectLOD>4</ObjectLOD>
			<IgnoreTerrain>1</IgnoreTerrain>
			<Position>15.739231,0.000000,-7.152241</Position>
			<Rotation>0.000000,0.450000,0.000000</Rotation>
			<RotationSpeed>0.000000,0.000000,0.000000</RotationSpeed>
			<Scale>1.0000</Scale>
			<BaseScale>1.0000</BaseScale>
		</TileDesignObject>
		<TileDesignObject InternalName="_obj12">
			<ObjectType>PropModelType</ObjectType>
			<ObjectDefName>K_Log_Small_01</ObjectDefName>
			<ObjectLOD>4</ObjectLOD>
			<IgnoreTerrain>1</IgnoreTerrain>
			<Position>20.859325,0.000000,-4.429028</Position>
			<Rotation>0.000000,-1.275000,0.000000</Rotation>
			<RotationSpeed>0.000000,0.000000,0.000000</RotationSpeed>
			<Scale>1.0000</Scale>
			<BaseScale>1.0000</BaseScale>
		</TileDesignObject>
		<TileDesignObject InternalName="_obj13">
			<ObjectType>PropModelType</ObjectType>
			<ObjectDefName>K_Log_Small_01</ObjectDefName>
			<ObjectLOD>4</ObjectLOD>
			<IgnoreTerrain>1</IgnoreTerrain>
			<Position>3.271778,0.000000,-8.647648</Position>
			<Rotation>0.000000,-2.250001,0.000000</Rotation>
			<RotationSpeed>0.000000,0.000000,0.000000</RotationSpeed>
			<Scale>1.0000</Scale>
			<BaseScale>1.0000</BaseScale>
		</TileDesignObject>
		<TileDesignObject InternalName="_obj14">
			<ObjectType>PropModelType</ObjectType>
			<ObjectDefName>K_Log_Big_01</ObjectDefName>
			<ObjectLOD>4</ObjectLOD>
			<IgnoreTerrain>1</IgnoreTerrain>
			<Position>2.311829,0.000000,-20.948044</Position>
			<Rotation>0.000000,-0.150000,0.000000</Rotation>
			<RotationSpeed>0.000000,0.000000,0.000000</RotationSpeed>
			<Scale>0.5600</Scale>
			<BaseScale>1.0000</BaseScale>
		</TileDesignObject>
		<TileDesignObject InternalName="_obj15">
			<ObjectType>PropModelType</ObjectType>
			<ObjectDefName>K_Log_Big_01</ObjectDefName>
			<ObjectLOD>4</ObjectLOD>
			<IgnoreTerrain>1</IgnoreTerrain>
			<Position>20.972626,0.000000,4.590424</Position>
			<Rotation>0.000000,1.350000,0.000000</Rotation>
			<RotationSpeed>0.000000,0.000000,0.000000</RotationSpeed>
			<Scale>0.5600</Scale>
			<BaseScale>1.0000</BaseScale>
		</TileDesignObject>
		<TileDesignObject InternalName="_obj16">
			<ObjectType>PropModelType</ObjectType>
			<ObjectDefName>K_Log_Small_01</ObjectDefName>
			<ObjectLOD>4</ObjectLOD>
			<IgnoreTerrain>1</IgnoreTerrain>
			<Position>18.680321,0.000000,13.804749</Position>
			<Rotation>0.000000,1.125000,0.000000</Rotation>
			<RotationSpeed>0.000000,0.000000,0.000000</RotationSpeed>
			<Scale>1.0000</Scale>
			<BaseScale>1.0000</BaseScale>
		</TileDesignObject>
		<TileDesignObject InternalName="_obj17">
			<ObjectType>PropModelType</ObjectType>
			<ObjectDefName>K_Log_Small_01</ObjectDefName>
			<ObjectLOD>4</ObjectLOD>
			<IgnoreTerrain>1</IgnoreTerrain>
			<Position>-7.289333,0.000000,-21.147346</Position>
			<Rotation>0.000000,0.225000,0.000000</Rotation>
			<RotationSpeed>0.000000,0.000000,0.000000</RotationSpeed>
			<Scale>1.0000</Scale>
			<BaseScale>1.0000</BaseScale>
		</TileDesignObject>
		<TileDesignObject InternalName="_obj18">
			<ObjectType>PropModelType</ObjectType>
			<ObjectDefName>K_Log_Small_01</ObjectDefName>
			<ObjectLOD>4</ObjectLOD>
			<IgnoreTerrain>1</IgnoreTerrain>
			<Position>-14.994450,0.000000,-19.312363</Position>
			<Rotation>0.000000,0.150000,0.000000</Rotation>
			<RotationSpeed>0.000000,0.000000,0.000000</RotationSpeed>
			<Scale>1.0000</Scale>
			<BaseScale>1.0000</BaseScale>
		</TileDesignObject>
		<TileDesignObject InternalName="_obj19">
			<ObjectType>PropModelType</ObjectType>
			<ObjectDefName>K_Log_Big_01</ObjectDefName>
			<ObjectLOD>4</ObjectLOD>
			<IgnoreTerrain>1</IgnoreTerrain>
			<Position>7.181786,0.000000,21.569801</Position>
			<Rotation>0.000000,-0.174533,0.000000</Rotation>
			<RotationSpeed>0.000000,0.000000,0.000000</RotationSpeed>
			<Scale>0.4800</Scale>
			<BaseScale>1.0000</BaseScale>
		</TileDesignObject>
		<TileDesignObject InternalName="_obj20">
			<ObjectType>PropModelType</ObjectType>
			<ObjectDefName>K_Log_Big_01</ObjectDefName>
			<ObjectLOD>4</ObjectLOD>
			<IgnoreTerrain>1</IgnoreTerrain>
			<Position>-19.250551,0.000000,-14.021727</Position>
			<Rotation>0.000000,1.500000,0.000000</Rotation>
			<RotationSpeed>0.000000,0.000000,0.000000</RotationSpeed>
			<Scale>0.4400</Scale>
			<BaseScale>1.0000</BaseScale>
		</TileDesignObject>
		<TileDesignObject InternalName="_obj21">
			<ObjectType>PropModelType</ObjectType>
			<ObjectDefName>K_Log_Small_01</ObjectDefName>
			<ObjectLOD>4</ObjectLOD>
			<IgnoreTerrain>1</IgnoreTerrain>
			<Position>6.750381,0.000000,-15.318184</Position>
			<Rotation>0.000000,1.200000,0.000000</Rotation>
			<RotationSpeed>0.000000,0.000000,0.000000</RotationSpeed>
			<Scale>1.0000</Scale>
			<BaseScale>1.0000</BaseScale>
		</TileDesignObject>
		<TileDesignObject InternalName="_obj22">
			<ObjectType>PropModelType</ObjectType>
			<ObjectDefName>K_Log_Small_01</ObjectDefName>
			<ObjectLOD>4</ObjectLOD>
			<IgnoreTerrain>1</IgnoreTerrain>
			<Position>15.080132,0.000000,20.402878</Position>
			<Rotation>0.000000,0.900000,0.000000</Rotation>
			<RotationSpeed>0.000000,0.000000,0.000000</RotationSpeed>
			<Scale>1.0000</Scale>
			<BaseScale>1.0000</BaseScale>
		</TileDesignObject>
		<TileDesignObject InternalName="_obj23">
			<ObjectType>PropModelType</ObjectType>
			<ObjectDefName>Artifact_SmallDeadTree4</ObjectDefName>
			<ObjectLOD>5</ObjectLOD>
			<IgnoreTerrain>1</IgnoreTerrain>
			<Position>12.234901,4.000000,19.587128</Position>
			<Rotation>0.000000,1.575000,0.000000</Rotation>
			<RotationSpeed>0.000000,0.000000,0.000000</RotationSpeed>
			<Scale>0.7200</Scale>
			<BaseScale>1.0000</BaseScale>
		</TileDesignObject>
		<TileDesignObject InternalName="_obj24">
			<ObjectType>PropModelType</ObjectType>
			<ObjectDefName>TreeCard1</ObjectDefName>
			<ObjectLOD>5</ObjectLOD>
			<IgnoreTerrain>1</IgnoreTerrain>
			<Position>13.031082,22.000000,18.913132</Position>
			<Rotation>0.000000,0.000000,0.000000</Rotation>
			<RotationSpeed>0.000000,0.000000,0.000000</RotationSpeed>
			<Scale>1.6000</Scale>
			<BaseScale>10.0000</BaseScale>
		</TileDesignObject>
		<TileDesignObject InternalName="_obj25">
			<ObjectType>PropModelType</ObjectType>
			<ObjectDefName>TreeCard1</ObjectDefName>
			<ObjectLOD>5</ObjectLOD>
			<IgnoreTerrain>1</IgnoreTerrain>
			<Position>-16.255836,23.000000,-14.682739</Position>
			<Rotation>0.000000,0.000000,0.000000</Rotation>
			<RotationSpeed>0.000000,0.000000,0.000000</RotationSpeed>
			<Scale>1.6000</Scale>
			<BaseScale>10.0000</BaseScale>
		</TileDesignObject>
		<TileDesignObject InternalName="_obj26">
			<ObjectType>PropModelType</ObjectType>
			<ObjectDefName>TreeCard10</ObjectDefName>
			<ObjectLOD>6</ObjectLOD>
			<IgnoreTerrain>1</IgnoreTerrain>
			<Position>14.915756,18.000000,15.135559</Position>
			<Rotation>0.000000,0.000000,0.000000</Rotation>
			<RotationSpeed>0.000000,0.000000,0.000000</RotationSpeed>
			<Scale>1.3600</Scale>
			<BaseScale>10.0000</BaseScale>
		</TileDesignObject>
		<TileDesignObject InternalName="_obj27">
			<ObjectType>PropModelType</ObjectType>
			<ObjectDefName>TreeCard10</ObjectDefName>
			<ObjectLOD>6</ObjectLOD>
			<IgnoreTerrain>1</IgnoreTerrain>
			<Position>-19.761734,16.000000,-9.708713</Position>
			<Rotation>0.000000,0.000000,0.000000</Rotation>
			<RotationSpeed>0.000000,0.000000,0.000000</RotationSpeed>
			<Scale>1.3600</Scale>
			<BaseScale>10.0000</BaseScale>
		</TileDesignObject>
		<TileDesignObject InternalName="_obj28">
			<ObjectType>PropModelType</ObjectType>
			<ObjectDefName>TreeCard10</ObjectDefName>
			<ObjectLOD>5</ObjectLOD>
			<IgnoreTerrain>1</IgnoreTerrain>
			<Position>14.859100,16.000000,23.914490</Position>
			<Rotation>0.000000,0.000000,0.000000</Rotation>
			<RotationSpeed>0.000000,0.000000,0.000000</RotationSpeed>
			<Scale>1.3600</Scale>
			<BaseScale>10.0000</BaseScale>
		</TileDesignObject>
		<TileDesignObject InternalName="_obj29">
			<ObjectType>PropModelType</ObjectType>
			<ObjectDefName>TreeCard2</ObjectDefName>
			<ObjectLOD>6</ObjectLOD>
			<IgnoreTerrain>1</IgnoreTerrain>
			<Position>-17.647034,17.000000,-22.633377</Position>
			<Rotation>0.000000,0.000000,0.000000</Rotation>
			<RotationSpeed>0.000000,0.000000,0.000000</RotationSpeed>
			<Scale>1.2800</Scale>
			<BaseScale>10.0000</BaseScale>
		</TileDesignObject>
		<TileDesignObject InternalName="_obj30">
			<ObjectType>PropModelType</ObjectType>
			<ObjectDefName>TreeCard2</ObjectDefName>
			<ObjectLOD>6</ObjectLOD>
			<IgnoreTerrain>1</IgnoreTerrain>
			<Position>12.999123,22.000000,21.375854</Position>
			<Rotation>0.000000,0.000000,0.000000</Rotation>
			<RotationSpeed>0.000000,0.000000,0.000000</RotationSpeed>
			<Scale>1.2800</Scale>
			<BaseScale>10.0000</BaseScale>
		</TileDesignObject>
		<TileDesignObject InternalName="_obj31">
			<ObjectType>PropModelType</ObjectType>
			<ObjectDefName>TreeCard2</ObjectDefName>
			<ObjectLOD>5</ObjectLOD>
			<IgnoreTerrain>1</IgnoreTerrain>
			<Position>8.965755,18.000000,18.354248</Position>
			<Rotation>0.000000,0.000000,0.000000</Rotation>
			<RotationSpeed>0.000000,0.000000,0.000000</RotationSpeed>
			<Scale>1.2800</Scale>
			<BaseScale>10.0000</BaseScale>
		</TileDesignObject>
		<TileDesignObject InternalName="_obj32">
			<ObjectType>PropModelType</ObjectType>
			<ObjectDefName>TreeCard2</ObjectDefName>
			<ObjectLOD>5</ObjectLOD>
			<IgnoreTerrain>1</IgnoreTerrain>
			<Position>-20.712006,17.000000,-15.137619</Position>
			<Rotation>0.000000,0.000000,0.000000</Rotation>
			<RotationSpeed>0.000000,0.000000,0.000000</RotationSpeed>
			<Scale>1.2800</Scale>
			<BaseScale>10.0000</BaseScale>
		</TileDesignObject>
		<TileDesignObject InternalName="_obj33">
			<ObjectType>PropModelType</ObjectType>
			<ObjectDefName>TreeCard9</ObjectDefName>
			<ObjectLOD>6</ObjectLOD>
			<IgnoreTerrain>1</IgnoreTerrain>
			<Position>-11.588226,19.000000,-18.149029</Position>
			<Rotation>0.000000,0.000000,0.000000</Rotation>
			<RotationSpeed>0.000000,0.000000,0.000000</RotationSpeed>
			<Scale>1.2400</Scale>
			<BaseScale>10.0000</BaseScale>
		</TileDesignObject>
		<TileDesignObject InternalName="_obj34">
			<ObjectType>PropModelType</ObjectType>
			<ObjectDefName>SmallFertileGrove1</ObjectDefName>
			<ObjectLOD>5</ObjectLOD>
			<IgnoreTerrain>1</IgnoreTerrain>
			<Position>11.285019,0.000000,1.467054</Position>
			<Rotation>0.000000,-1.050000,0.000000</Rotation>
			<RotationSpeed>0.000000,0.000000,0.000000</RotationSpeed>
			<Scale>0.5600</Scale>
			<BaseScale>1.0000</BaseScale>
		</TileDesignObject>
		<TileDesignObject InternalName="_obj35">
			<ObjectType>PropModelType</ObjectType>
			<ObjectDefName>SmallFertileGrove1</ObjectDefName>
			<ObjectLOD>4</ObjectLOD>
			<IgnoreTerrain>1</IgnoreTerrain>
			<Position>13.644913,0.000000,14.887718</Position>
			<Rotation>0.000000,0.675000,0.000000</Rotation>
			<RotationSpeed>0.000000,0.000000,0.000000</RotationSpeed>
			<Scale>0.5600</Scale>
			<BaseScale>1.0000</BaseScale>
		</TileDesignObject>
		<TileDesignObject InternalName="_obj36">
			<ObjectType>PropModelType</ObjectType>
			<ObjectDefName>SmallFertileGrove2</ObjectDefName>
			<ObjectLOD>5</ObjectLOD>
			<IgnoreTerrain>1</IgnoreTerrain>
			<Position>16.494514,0.000000,10.215012</Position>
			<Rotation>0.000000,-4.050002,0.000000</Rotation>
			<RotationSpeed>0.000000,0.000000,0.000000</RotationSpeed>
			<Scale>0.8000</Scale>
			<BaseScale>1.0000</BaseScale>
		</TileDesignObject>
		<TileDesignObject InternalName="_obj37">
			<ObjectType>PropModelType</ObjectType>
			<ObjectDefName>SmallFertileGrove3</ObjectDefName>
			<ObjectLOD>6</ObjectLOD>
			<IgnoreTerrain>1</IgnoreTerrain>
			<Position>16.154884,0.000000,2.993782</Position>
			<Rotation>0.000000,-0.975000,0.000000</Rotation>
			<RotationSpeed>0.000000,0.000000,0.000000</RotationSpeed>
			<Scale>0.6800</Scale>
			<BaseScale>1.0000</BaseScale>
		</TileDesignObject>
		<TileDesignObject InternalName="_obj38">
			<ObjectType>PropModelType</ObjectType>
			<ObjectDefName>SmallFertileGrove3</ObjectDefName>
			<ObjectLOD>5</ObjectLOD>
			<IgnoreTerrain>1</IgnoreTerrain>
			<Position>16.631989,0.000000,-2.149754</Position>
			<Rotation>0.000000,-2.850001,0.000000</Rotation>
			<RotationSpeed>0.000000,0.000000,0.000000</RotationSpeed>
			<Scale>0.7600</Scale>
			<BaseScale>1.0000</BaseScale>
		</TileDesignObject>
		<TileDesignObject InternalName="_obj39">
			<ObjectType>PropModelType</ObjectType>
			<ObjectDefName>K_Wood_Flag_Poll_01</ObjectDefName>
			<ObjectLOD>4</ObjectLOD>
			<IgnoreTerrain>1</IgnoreTerrain>
			<Position>18.486679,0.000000,-6.535904</Position>
			<Rotation>0.087266,1.745329,0.000000</Rotation>
			<RotationSpeed>0.000000,0.000000,0.000000</RotationSpeed>
			<Scale>1.0000</Scale>
			<BaseScale>1.0000</BaseScale>
		</TileDesignObject>
		<TileDesignObject InternalName="_obj40">
			<ObjectType>PropModelType</ObjectType>
			<ObjectDefName>K_Wood_Flag_Poll_01</ObjectDefName>
			<ObjectLOD>4</ObjectLOD>
			<IgnoreTerrain>1</IgnoreTerrain>
			<Position>6.031464,0.000000,-18.556480</Position>
			<Rotation>-0.087266,0.000000,0.000000</Rotation>
			<RotationSpeed>0.000000,0.000000,0.000000</RotationSpeed>
			<Scale>1.0000</Scale>
			<BaseScale>1.0000</BaseScale>
		</TileDesignObject>
		<TileDesignObject InternalName="_obj41">
			<ObjectType>PropModelType</ObjectType>
			<ObjectDefName>K_Rope_01</ObjectDefName>
			<ObjectLOD>5</ObjectLOD>
			<IgnoreTerrain>1</IgnoreTerrain>
			<Position>10.482494,18.000000,2.398695</Position>
			<Rotation>0.000000,0.750000,0.174533</Rotation>
			<RotationSpeed>0.000000,0.000000,0.000000</RotationSpeed>
			<Scale>1.0000</Scale>
			<BaseScale>1.0000</BaseScale>
		</TileDesignObject>
		<TileDesignObject InternalName="_obj42">
			<ObjectType>PropModelType</ObjectType>
			<ObjectDefName>K_Rope_01</ObjectDefName>
			<ObjectLOD>5</ObjectLOD>
			<IgnoreTerrain>1</IgnoreTerrain>
			<Position>-1.391346,18.000000,-10.826117</Position>
			<Rotation>0.000000,0.900000,0.174533</Rotation>
			<RotationSpeed>0.000000,0.000000,0.000000</RotationSpeed>
			<Scale>0.9200</Scale>
			<BaseScale>1.0000</BaseScale>
		</TileDesignObject>
		<TileDesignObject InternalName="_obj43">
			<ObjectType>PropModelType</ObjectType>
			<ObjectDefName>K_Rope_01</ObjectDefName>
			<ObjectLOD>5</ObjectLOD>
			<IgnoreTerrain>1</IgnoreTerrain>
			<Position>12.894951,20.000000,-13.699989</Position>
			<Rotation>0.000000,-0.750000,0.000000</Rotation>
			<RotationSpeed>0.000000,0.000000,0.000000</RotationSpeed>
			<Scale>0.7200</Scale>
			<BaseScale>1.0000</BaseScale>
		</TileDesignObject>
		<TileDesignObject InternalName="_obj44">
			<ObjectType>PropModelType</ObjectType>
			<ObjectDefName>SingleWheat</ObjectDefName>
			<ObjectLOD>6</ObjectLOD>
			<IgnoreTerrain>1</IgnoreTerrain>
			<Position>18.338085,21.000000,-4.864042</Position>
			<Rotation>3.141593,0.000000,0.000000</Rotation>
			<RotationSpeed>0.000000,0.000000,0.000000</RotationSpeed>
			<Scale>1.0000</Scale>
			<BaseScale>1.0000</BaseScale>
		</TileDesignObject>
		<TileDesignObject InternalName="_obj45">
			<ObjectType>PropModelType</ObjectType>
			<ObjectDefName>SingleWheat</ObjectDefName>
			<ObjectLOD>6</ObjectLOD>
			<IgnoreTerrain>1</IgnoreTerrain>
			<Position>15.608170,20.000000,-2.380738</Position>
			<Rotation>3.141593,-0.610865,0.000000</Rotation>
			<RotationSpeed>0.000000,0.000000,0.000000</RotationSpeed>
			<Scale>1.0000</Scale>
			<BaseScale>1.0000</BaseScale>
		</TileDesignObject>
		<TileDesignObject InternalName="_obj46">
			<ObjectType>PropModelType</ObjectType>
			<ObjectDefName>SingleWheat</ObjectDefName>
			<ObjectLOD>6</ObjectLOD>
			<IgnoreTerrain>1</IgnoreTerrain>
			<Position>12.521931,19.000000,0.039769</Position>
			<Rotation>3.141593,0.000000,0.000000</Rotation>
			<RotationSpeed>0.000000,0.000000,0.000000</RotationSpeed>
			<Scale>1.0000</Scale>
			<BaseScale>1.0000</BaseScale>
		</TileDesignObject>
		<TileDesignObject InternalName="_obj47">
			<ObjectType>PropModelType</ObjectType>
			<ObjectDefName>SingleWheat</ObjectDefName>
			<ObjectLOD>6</ObjectLOD>
			<IgnoreTerrain>1</IgnoreTerrain>
			<Position>8.047723,18.000000,4.022210</Position>
			<Rotation>3.141593,0.349066,0.000000</Rotation>
			<RotationSpeed>0.000000,0.000000,0.000000</RotationSpeed>
			<Scale>1.0000</Scale>
			<BaseScale>1.0000</BaseScale>
		</TileDesignObject>
		<TileDesignObject InternalName="_obj48">
			<ObjectType>PropModelType</ObjectType>
			<ObjectDefName>SingleWheat</ObjectDefName>
			<ObjectLOD>6</ObjectLOD>
			<IgnoreTerrain>1</IgnoreTerrain>
			<Position>9.633752,18.000000,2.765366</Position>
			<Rotation>3.141593,0.000000,0.000000</Rotation>
			<RotationSpeed>0.000000,0.000000,0.000000</RotationSpeed>
			<Scale>1.0000</Scale>
			<BaseScale>1.0000</BaseScale>
		</TileDesignObject>
		<TileDesignObject InternalName="_obj49">
			<ObjectType>PropModelType</ObjectType>
			<ObjectDefName>FallenPlant_Mushroom2</ObjectDefName>
			<ObjectLOD>6</ObjectLOD>
			<IgnoreTerrain>1</IgnoreTerrain>
			<Position>-3.676911,18.000000,-8.255974</Position>
			<Rotation>3.141593,0.000000,0.000000</Rotation>
			<RotationSpeed>0.000000,0.000000,0.000000</RotationSpeed>
			<Scale>0.5600</Scale>
			<BaseScale>1.0000</BaseScale>
		</TileDesignObject>
		<TileDesignObject InternalName="_obj50">
			<ObjectType>PropModelType</ObjectType>
			<ObjectDefName>FallenPlant_Mushroom2</ObjectDefName>
			<ObjectLOD>6</ObjectLOD>
			<IgnoreTerrain>1</IgnoreTerrain>
			<Position>-1.334271,18.000000,-10.833771</Position>
			<Rotation>3.141593,2.025001,0.000000</Rotation>
			<RotationSpeed>0.000000,0.000000,0.000000</RotationSpeed>
			<Scale>0.5600</Scale>
			<BaseScale>1.0000</BaseScale>
		</TileDesignObject>
		<TileDesignObject InternalName="_obj51">
			<ObjectType>PropModelType</ObjectType>
			<ObjectDefName>SingleCorn</ObjectDefName>
			<ObjectLOD>6</ObjectLOD>
			<IgnoreTerrain>1</IgnoreTerrain>
			<Position>0.700947,19.000000,-13.348335</Position>
			<Rotation>3.141593,0.000000,0.000000</Rotation>
			<RotationSpeed>0.000000,0.000000,0.000000</RotationSpeed>
			<Scale>0.4400</Scale>
			<BaseScale>1.0000</BaseScale>
		</TileDesignObject>
		<TileDesignObject InternalName="_obj52">
			<ObjectType>PropModelType</ObjectType>
			<ObjectDefName>SingleCorn</ObjectDefName>
			<ObjectLOD>6</ObjectLOD>
			<IgnoreTerrain>1</IgnoreTerrain>
			<Position>2.076041,19.000000,-14.885963</Position>
			<Rotation>3.141593,0.000000,0.000000</Rotation>
			<RotationSpeed>0.000000,0.000000,0.000000</RotationSpeed>
			<Scale>0.5600</Scale>
			<BaseScale>1.0000</BaseScale>
		</TileDesignObject>
		<TileDesignObject InternalName="_obj53">
			<ObjectType>PropModelType</ObjectType>
			<ObjectDefName>SingleCorn</ObjectDefName>
			<ObjectLOD>6</ObjectLOD>
			<IgnoreTerrain>1</IgnoreTerrain>
			<Position>3.473265,20.000000,-17.161919</Position>
			<Rotation>3.141593,0.000000,0.000000</Rotation>
			<RotationSpeed>0.000000,0.000000,0.000000</RotationSpeed>
			<Scale>0.6800</Scale>
			<BaseScale>1.0000</BaseScale>
		</TileDesignObject>
		<TileDesignObject InternalName="_obj54">
			<ObjectType>PropModelType</ObjectType>
			<ObjectDefName>Artifact_Sack5</ObjectDefName>
			<ObjectLOD>6</ObjectLOD>
			<IgnoreTerrain>1</IgnoreTerrain>
			<Position>-6.558884,15.000000,-3.446056</Position>
			<Rotation>-1.658063,0.000000,0.000000</Rotation>
			<RotationSpeed>0.000000,0.000000,0.000000</RotationSpeed>
			<Scale>1.0000</Scale>
			<BaseScale>0.5000</BaseScale>
		</TileDesignObject>
		<TileDesignObject InternalName="_obj55">
			<ObjectType>PropModelType</ObjectType>
			<ObjectDefName>Artifact_Sack5</ObjectDefName>
			<ObjectLOD>6</ObjectLOD>
			<IgnoreTerrain>1</IgnoreTerrain>
			<Position>6.525047,15.000000,7.154394</Position>
			<Rotation>-1.658063,1.350000,0.000000</Rotation>
			<RotationSpeed>0.000000,0.000000,0.000000</RotationSpeed>
			<Scale>1.0000</Scale>
			<BaseScale>0.5000</BaseScale>
		</TileDesignObject>
		<TileDesignObject InternalName="_obj56">
			<ObjectType>PropModelType</ObjectType>
			<ObjectDefName>K_Stone_Door_01</ObjectDefName>
			<ObjectLOD>5</ObjectLOD>
			<IgnoreTerrain>1</IgnoreTerrain>
			<Position>-16.310780,0.000000,16.406097</Position>
			<Rotation>0.000000,-0.837266,0.000000</Rotation>
			<RotationSpeed>0.000000,0.000000,0.000000</RotationSpeed>
			<Scale>1.2400</Scale>
			<BaseScale>1.0000</BaseScale>
		</TileDesignObject>
		<TileDesignObject InternalName="_obj57">
			<ObjectType>PropModelType</ObjectType>
			<ObjectDefName>K_Chimney_02</ObjectDefName>
			<ObjectLOD>5</ObjectLOD>
			<IgnoreTerrain>1</IgnoreTerrain>
			<Position>-16.429760,7.000000,16.417503</Position>
			<Rotation>-1.658063,-0.825000,0.000000</Rotation>
			<RotationSpeed>0.000000,0.000000,0.000000</RotationSpeed>
			<Scale>0.6800</Scale>
			<BaseScale>1.0000</BaseScale>
		</TileDesignObject>
		<TileDesignObject InternalName="_obj58">
			<ObjectType>PropModelType</ObjectType>
			<ObjectDefName>RobedTalking2</ObjectDefName>
			<ObjectLOD>6</ObjectLOD>
			<IgnoreTerrain>1</IgnoreTerrain>
			<Position>-1.571207,6.000000,2.038137</Position>
			<Rotation>0.000000,-0.750000,0.000000</Rotation>
			<RotationSpeed>0.000000,0.000000,0.000000</RotationSpeed>
			<Scale>1.0000</Scale>
			<BaseScale>0.1300</BaseScale>
		</TileDesignObject>
		<TileDesignObject InternalName="_obj59">
			<ObjectType>PropModelType</ObjectType>
			<ObjectDefName>FarmerTalking2</ObjectDefName>
			<ObjectLOD>6</ObjectLOD>
			<IgnoreTerrain>1</IgnoreTerrain>
			<Position>9.727638,0.000000,-6.297394</Position>
			<Rotation>0.000000,1.950000,0.000000</Rotation>
			<RotationSpeed>0.000000,0.000000,0.000000</RotationSpeed>
			<Scale>1.0000</Scale>
			<BaseScale>0.1300</BaseScale>
		</TileDesignObject>
		<TileDesignObject InternalName="_obj60">
			<ObjectType>PropModelType</ObjectType>
			<ObjectDefName>FemaleFarmerTalking1</ObjectDefName>
			<ObjectLOD>6</ObjectLOD>
			<IgnoreTerrain>1</IgnoreTerrain>
			<Position>8.787075,0.000000,-11.132439</Position>
			<Rotation>0.000000,2.475001,0.000000</Rotation>
			<RotationSpeed>0.000000,0.000000,0.000000</RotationSpeed>
			<Scale>1.0000</Scale>
			<BaseScale>0.1300</BaseScale>
		</TileDesignObject>
		<TileDesignObject InternalName="_obj61">
			<ObjectType>PropModelType</ObjectType>
			<ObjectDefName>MaleAtMarket</ObjectDefName>
			<ObjectLOD>6</ObjectLOD>
			<IgnoreTerrain>1</IgnoreTerrain>
			<Position>13.400089,0.000000,-12.088730</Position>
			<Rotation>0.000000,2.100000,0.000000</Rotation>
			<RotationSpeed>0.000000,0.000000,0.000000</RotationSpeed>
			<Scale>1.0000</Scale>
			<BaseScale>0.1300</BaseScale>
		</TileDesignObject>
		<TileDesignObject InternalName="_obj62">
			<ObjectType>PropModelType</ObjectType>
			<ObjectDefName>FallenPlant_Mushroom2</ObjectDefName>
			<ObjectLOD>6</ObjectLOD>
			<IgnoreTerrain>1</IgnoreTerrain>
			<Position>0.408158,0.000000,-9.479614</Position>
			<Rotation>0.000000,1.575000,0.000000</Rotation>
			<RotationSpeed>0.000000,0.000000,0.000000</RotationSpeed>
			<Scale>0.7600</Scale>
			<BaseScale>1.0000</BaseScale>
		</TileDesignObject>
		<TileDesignObject InternalName="_obj63">
			<ObjectType>PropModelType</ObjectType>
			<ObjectDefName>FallenPlant_Mushroom2</ObjectDefName>
			<ObjectLOD>6</ObjectLOD>
			<IgnoreTerrain>1</IgnoreTerrain>
			<Position>2.616280,0.000000,-14.602898</Position>
			<Rotation>0.000000,-1.200000,0.000000</Rotation>
			<RotationSpeed>0.000000,0.000000,0.000000</RotationSpeed>
			<Scale>0.7600</Scale>
			<BaseScale>1.0000</BaseScale>
		</TileDesignObject>
		<TileDesignObject InternalName="_obj64">
			<ObjectType>PropModelType</ObjectType>
			<ObjectDefName>FallenPlant_SpikePod1</ObjectDefName>
			<ObjectLOD>5</ObjectLOD>
			<IgnoreTerrain>1</IgnoreTerrain>
			<Position>-2.287067,1.000000,-12.403442</Position>
			<Rotation>0.000000,1.425000,0.000000</Rotation>
			<RotationSpeed>0.000000,0.000000,0.000000</RotationSpeed>
			<Scale>0.4800</Scale>
			<BaseScale>1.0000</BaseScale>
		</TileDesignObject>
		<TileDesignObject InternalName="_obj65">
			<ObjectType>PropModelType</ObjectType>
			<ObjectDefName>FallenPlant_SpikePod1</ObjectDefName>
			<ObjectLOD>5</ObjectLOD>
			<IgnoreTerrain>1</IgnoreTerrain>
			<Position>0.267132,0.000000,-17.503738</Position>
			<Rotation>0.000000,1.471263,0.000000</Rotation>
			<RotationSpeed>0.000000,0.000000,0.000000</RotationSpeed>
			<Scale>0.5200</Scale>
			<BaseScale>1.0000</BaseScale>
		</TileDesignObject>
		<TileDesignObject InternalName="_obj66">
			<ObjectType>PropModelType</ObjectType>
			<ObjectDefName>FallenPlant_SpikePod2</ObjectDefName>
			<ObjectLOD>4</ObjectLOD>
			<IgnoreTerrain>1</IgnoreTerrain>
			<Position>-4.035292,0.000000,-19.005280</Position>
			<Rotation>0.000000,0.000000,0.000000</Rotation>
			<RotationSpeed>0.000000,0.000000,0.000000</RotationSpeed>
			<Scale>0.6400</Scale>
			<BaseScale>1.0000</BaseScale>
		</TileDesignObject>
		<TileDesignObject InternalName="_obj67">
			<ObjectType>PropModelType</ObjectType>
			<ObjectDefName>FallenPlant_SpikePod2</ObjectDefName>
			<ObjectLOD>6</ObjectLOD>
			<IgnoreTerrain>1</IgnoreTerrain>
			<Position>-6.994453,0.000000,-12.648560</Position>
			<Rotation>0.000000,-0.900000,0.000000</Rotation>
			<RotationSpeed>0.000000,0.000000,0.000000</RotationSpeed>
			<Scale>0.6400</Scale>
			<BaseScale>1.0000</BaseScale>
		</TileDesignObject>
		<TileDesignObject InternalName="_obj68">
			<ObjectType>PropModelType</ObjectType>
			<ObjectDefName>FallenPlant_SpikePod2</ObjectDefName>
			<ObjectLOD>6</ObjectLOD>
			<IgnoreTerrain>1</IgnoreTerrain>
			<Position>-6.081770,0.000000,-15.430580</Position>
			<Rotation>0.000000,-0.225000,0.000000</Rotation>
			<RotationSpeed>0.000000,0.000000,0.000000</RotationSpeed>
			<Scale>0.5600</Scale>
			<BaseScale>1.0000</BaseScale>
		</TileDesignObject>
		<TileDesignObject InternalName="_obj69">
			<ObjectType>PropModelType</ObjectType>
			<ObjectDefName>FallenPlant_FungusStack1</ObjectDefName>
			<ObjectLOD>5</ObjectLOD>
			<IgnoreTerrain>1</IgnoreTerrain>
			<Position>-11.247768,0.000000,-13.334595</Position>
			<Rotation>0.000000,1.200000,0.000000</Rotation>
			<RotationSpeed>0.000000,0.000000,0.000000</RotationSpeed>
			<Scale>0.5200</Scale>
			<BaseScale>1.0000</BaseScale>
		</TileDesignObject>
		<TileDesignObject InternalName="_obj70">
			<ObjectType>PropModelType</ObjectType>
			<ObjectDefName>BlueFlowers1</ObjectDefName>
			<ObjectLOD>6</ObjectLOD>
			<IgnoreTerrain>1</IgnoreTerrain>
			<Position>-11.492447,0.000000,-14.964706</Position>
			<Rotation>0.000000,-0.450000,0.000000</Rotation>
			<RotationSpeed>0.000000,0.000000,0.000000</RotationSpeed>
			<Scale>0.4800</Scale>
			<BaseScale>1.0000</BaseScale>
		</TileDesignObject>
		<TileDesignObject InternalName="_obj71">
			<ObjectType>PropModelType</ObjectType>
			<ObjectDefName>BlueFlowers1</ObjectDefName>
			<ObjectLOD>4</ObjectLOD>
			<IgnoreTerrain>1</IgnoreTerrain>
			<Position>-3.951630,0.000000,-15.442139</Position>
			<Rotation>0.000000,-1.275000,0.000000</Rotation>
			<RotationSpeed>0.000000,0.000000,0.000000</RotationSpeed>
			<Scale>0.4800</Scale>
			<BaseScale>1.0000</BaseScale>
		</TileDesignObject>
		<TileDesignObject InternalName="_obj72">
			<ObjectType>PropModelType</ObjectType>
			<ObjectDefName>YellowFlowers1</ObjectDefName>
			<ObjectLOD>4</ObjectLOD>
			<IgnoreTerrain>1</IgnoreTerrain>
			<Position>-0.018665,0.000000,-13.512192</Position>
			<Rotation>0.000000,-1.725000,0.000000</Rotation>
			<RotationSpeed>0.000000,0.000000,0.000000</RotationSpeed>
			<Scale>0.2800</Scale>
			<BaseScale>1.0000</BaseScale>
		</TileDesignObject>
		<TileDesignObject InternalName="_obj73">
			<ObjectType>PropModelType</ObjectType>
			<ObjectDefName>FallenPlant_FungusStack2</ObjectDefName>
			<ObjectLOD>5</ObjectLOD>
			<IgnoreTerrain>1</IgnoreTerrain>
			<Position>-9.557297,0.000000,-18.016830</Position>
			<Rotation>0.000000,-1.725000,0.000000</Rotation>
			<RotationSpeed>0.000000,0.000000,0.000000</RotationSpeed>
			<Scale>0.5200</Scale>
			<BaseScale>1.0000</BaseScale>
		</TileDesignObject>
		<TileDesignObject InternalName="_obj74">
			<ObjectType>PropModelType</ObjectType>
			<ObjectDefName>K_Barrel_02</ObjectDefName>
			<ObjectLOD>6</ObjectLOD>
			<IgnoreTerrain>1</IgnoreTerrain>
			<Position>-15.151544,4.000000,21.093498</Position>
			<Rotation>3.141592,0.225000,0.000000</Rotation>
			<RotationSpeed>0.000000,0.000000,0.000000</RotationSpeed>
			<Scale>0.8000</Scale>
			<BaseScale>1.0000</BaseScale>
		</TileDesignObject>
		<TileDesignObject InternalName="_obj75">
			<ObjectType>PropModelType</ObjectType>
			<ObjectDefName>K_Barrel_02</ObjectDefName>
			<ObjectLOD>6</ObjectLOD>
			<IgnoreTerrain>1</IgnoreTerrain>
			<Position>-21.398876,0.000000,15.603792</Position>
			<Rotation>0.000000,-0.075000,0.000000</Rotation>
			<RotationSpeed>0.000000,0.000000,0.000000</RotationSpeed>
			<Scale>0.7200</Scale>
			<BaseScale>1.0000</BaseScale>
		</TileDesignObject>
		<TileDesignPath InternalName="_path0"/>
		<TileDesignPath InternalName="_path1"/>
		<EffectTrigger InternalName="ChimneySmokeNew">
			<EffectName>ChimneySmokeNew</EffectName>
			<LocalPosition>-14.884259,28.000000,1.545139</LocalPosition>
			<Scale>0.4400</Scale>
			<IndefiniteRepeat>1</IndefiniteRepeat>
			<SpawnOnCreation>1</SpawnOnCreation>
		</EffectTrigger>
	</TileDesign>
</TileDesigns>
